restpylot/__init__.py
restpylot/main.py
restpylot-0.1.1.dist-info/LICENSE
restpylot-0.1.1.dist-info/METADATA
restpylot-0.1.1.dist-info/WHEEL
restpylot-0.1.1.dist-info/RECORD
